[
   {
      "id": "2ed7aa6b-6d2e-4853-b2d5-9c606912574f",
      "title": "Mate Forrado",
      "category": "Oferta",
      "character": "Productos Artesanales",
      "region": "Pampeana",
      "price": "250000",
      "discount": "20",
      "description": "Mate de Palo Santo",
      "cant": "200",
      "cantMin": "10",
      "image": "1693221274195_products_.jpg"
   },
   {
      "id": "35702a14-cba7-4ac9-9e1a-356308fc3803",
      "title": "Bombilla de Plata",
      "category": "Mas Visitadas",
      "character": "Productos Artesanales",
      "region": "Pampeana",
      "price": "30000",
      "discount": "20",
      "description": "Elaborado con plata 900",
      "cant": "300",
      "cantMin": "15",
      "image": "1693221355485_products_.jpg"
   },
   {
      "id": "581e26c6-a4f5-4681-94a1-80b614db9255",
      "title": "Poncho ",
      "category": "New",
      "character": "Vestimenta",
      "region": "Pampeana",
      "price": "250000",
      "discount": "20",
      "description": "Elaborado con lana de Alpaca",
      "cant": "3000",
      "cantMin": "20",
      "image": "1693221509288_products_.jpg"
   },
   {
      "id": "be1b1291-aa95-4a1c-aab4-db508862602b",
      "title": "Tabla de Asado",
      "category": "New",
      "character": "Productos Artesanales",
      "region": "Pampeana",
      "price": "250000",
      "discount": "20",
      "description": "Madera de pinno",
      "cant": "500",
      "cantMin": "20",
      "image": "1693221732155_products_.jpg"
   },
   {
      "id": "f1623e57-af14-451f-9d40-9550e64bdd99",
      "title": "Destapador",
      "category": "Oferta",
      "character": "Productos Artesanales",
      "region": "Pampeana",
      "price": "150000",
      "discount": "20",
      "description": "Tabla de Pino",
      "cant": "3000",
      "cantMin": "20",
      "image": "1693221802827_products_.jpg"
   },
   {
      "id": "3d965384-3113-40b7-a3e8-657c58a5610b",
      "title": "Cinturon",
      "category": "Oferta",
      "character": "Vestimenta",
      "region": "Pampeana",
      "price": "65000",
      "discount": "10",
      "description": "Cuero de lombris",
      "cant": "200",
      "cantMin": "10",
      "image": "1693221876951_products_.jpg"
   },
   {
      "id": "1e3e2e9a-dd32-4c1d-81e5-72cbe6c6f48a",
      "title": "Termo",
      "category": "New",
      "character": "Regionales",
      "region": "Pampeana",
      "price": "54000",
      "discount": "",
      "description": "Termo Nativo ",
      "cant": "3000",
      "cantMin": "10",
      "image": "1693222044487_products_.jpg"
   }
]